MANIFEST.in
README.txt
setup.py
config/config.conf
config/pscripts.yaml
config/update_external_ip.service
config/urls.yaml
pscripts/__init__.py
pscripts/busy_or_not.py
pscripts/chroot_helper.py
pscripts/deployment.py
pscripts/disks.py
pscripts/external_ip_address.py
pscripts/hdmi_control.py
pscripts/html_access.py
pscripts/laptop_battery.py
pscripts/test_setup.py
pscripts.egg-info/PKG-INFO
pscripts.egg-info/SOURCES.txt
pscripts.egg-info/dependency_links.txt
pscripts.egg-info/requires.txt
pscripts.egg-info/top_level.txt
scripts/cp_exe_2_chroot_jail
scripts/hdmi_brightness
scripts/laptop_battery
scripts/python-deployment
scripts/update_external_ip