Metadata-Version: 1.1
Name: pscripts
Version: 0.1.160
Summary: Automation Scripts for Linux
Home-page: www.google.com
Author: Fenton Travers
Author-email: fenton.travers@gmail.com
License: Creative Commons Attribution-Noncommercial-Share Alike license
Platform: UNKNOWN
Classifier: Programming Language :: Python :: 3.3
Classifier: Development Status :: 4 - Beta
Classifier: Intended Audience :: Developers
Classifier: Natural Language :: English
Classifier: Operating System :: POSIX :: Linux
Classifier: Topic :: System :: Systems Administration
Classifier: Topic :: Utilities
